source_zendesk_support/__init__.py
source_zendesk_support/components.py
source_zendesk_support/manifest.yaml
source_zendesk_support/run.py
source_zendesk_support/schemas/account_attributes.json
source_zendesk_support/schemas/article_attachments.json
source_zendesk_support/schemas/article_comments.json
source_zendesk_support/schemas/articles.json
source_zendesk_support/schemas/attribute_definitions.json
source_zendesk_support/schemas/audit_logs.json
source_zendesk_support/schemas/automations.json
source_zendesk_support/schemas/brands.json
source_zendesk_support/schemas/categories.json
source_zendesk_support/schemas/custom_roles.json
source_zendesk_support/schemas/deleted_tickets.json
source_zendesk_support/schemas/group_memberships.json
source_zendesk_support/schemas/groups.json
source_zendesk_support/schemas/macros.json
source_zendesk_support/schemas/organization_fields.json
source_zendesk_support/schemas/organization_memberships.json
source_zendesk_support/schemas/organizations.json
source_zendesk_support/schemas/post_comments.json
source_zendesk_support/schemas/posts.json
source_zendesk_support/schemas/satisfaction_ratings.json
source_zendesk_support/schemas/schedules.json
source_zendesk_support/schemas/sections.json
source_zendesk_support/schemas/shared/attachments.json
source_zendesk_support/schemas/shared/metadata.json
source_zendesk_support/schemas/shared/tickets.json
source_zendesk_support/schemas/shared/via.json
source_zendesk_support/schemas/shared/via_channel.json
source_zendesk_support/schemas/sla_policies.json
source_zendesk_support/schemas/tags.json
source_zendesk_support/schemas/ticket_activities.json
source_zendesk_support/schemas/ticket_audits.json
source_zendesk_support/schemas/ticket_comments.json
source_zendesk_support/schemas/ticket_fields.json
source_zendesk_support/schemas/ticket_forms.json
source_zendesk_support/schemas/ticket_metric_events.json
source_zendesk_support/schemas/ticket_metrics.json
airbyte_source_zendesk_support-4.9.1.dist-info/METADATA
airbyte_source_zendesk_support-4.9.1.dist-info/WHEEL
airbyte_source_zendesk_support-4.9.1.dist-info/entry_points.txt
airbyte_source_zendesk_support-4.9.1.dist-info/RECORD
